blueprints/__init__.py
blueprints/adaptive_generation_strategist.py
blueprints/adaptive_prompt_generator.py
blueprints/agentic_resolver.py
blueprints/claude_parser.py
blueprints/code_generator.py
blueprints/config.py
blueprints/constants.py
blueprints/dependency_manager.py
blueprints/factory.py
blueprints/generator.py
blueprints/intelligent_context_curator.py
blueprints/iterative_quality_improver.py
blueprints/logging_config.py
blueprints/natural_generator.py
blueprints/parser.py
blueprints/project_generator.py
blueprints/prompt_builder.py
blueprints/resolver.py
blueprints/utils.py
blueprints/verifier.py
blueprints/cli/__init__.py
blueprints/cli/main.py
blueprints_md-1.0.1.dist-info/METADATA
blueprints_md-1.0.1.dist-info/WHEEL
blueprints_md-1.0.1.dist-info/entry_points.txt
blueprints_md-1.0.1.dist-info/licenses/LICENSE
blueprints_md-1.0.1.dist-info/RECORD
